[{"url": "Y.Event.API.html#method_after", "access": "", "host": "Y.Event.API", "type": "method", "name": "after"}, {"url": "Y.Event.API.html#method_bubbleTo", "access": "", "host": "Y.Event.API", "type": "method", "name": "bubbleTo"}, {"url": "Y.Event.API.html#property_defaultEvent", "access": "", "host": "Y.Event.API", "type": "property", "name": "defaultEvent"}, {"url": "Y.Event.API.html#method_detach", "access": "", "host": "Y.Event.API", "type": "method", "name": "detach"}, {"url": "Y.Event.API.html#property__event", "access": "protected", "host": "Y.Event.API", "type": "property", "name": "_event"}, {"url": "Y.Event.API.html#property_eventDef.allowDups", "access": "protected", "host": "Y.Event.API", "type": "property", "name": "eventDef.allowDups"}, {"url": "Y.Event.API.html#method_eventDef.destroy", "access": "protected", "host": "Y.Event.API", "type": "method", "name": "eventDef.destroy"}, {"url": "Y.Event.API.html#method_eventDef.detach", "access": "protected", "host": "Y.Event.API", "type": "method", "name": "eventDef.detach"}, {"url": "Y.Event.API.html#method_eventDef.filterSubs", "access": "protected", "host": "Y.Event.API", "type": "method", "name": "eventDef.filterSubs"}, {"url": "Y.Event.API.html#method_eventDef.fire", "access": "protected", "host": "Y.Event.API", "type": "method", "name": "eventDef.fire"}, {"url": "Y.Event.API.html#method_eventDef.generateEvent", "access": "protected", "host": "Y.Event.API", "type": "method", "name": "eventDef.generateEvent"}, {"url": "Y.Event.API.html#method_eventDef._immediate", "access": "protected", "host": "Y.Event.API", "type": "method", "name": "eventDef._immediate"}, {"url": "Y.Event.API.html#method_eventDef.init", "access": "protected", "host": "Y.Event.API", "type": "method", "name": "eventDef.init"}, {"url": "Y.Event.API.html#method_eventDef.notify", "access": "protected", "host": "Y.Event.API", "type": "method", "name": "eventDef.notify"}, {"url": "Y.Event.API.html#method_eventDef.subscribe", "access": "protected", "host": "Y.Event.API", "type": "method", "name": "eventDef.subscribe"}, {"url": "Y.Event.API.html#method_eventDef.test", "access": "protected", "host": "Y.Event.API", "type": "method", "name": "eventDef.test"}, {"url": "Y.Event.API.html#method_fire", "access": "", "host": "Y.Event.API", "type": "method", "name": "fire"}, {"url": "Y.Event.API.html#method_getEvent", "access": "", "host": "Y.Event.API", "type": "method", "name": "getEvent"}, {"url": "Y.Event.API.html#method_hasSubscribers", "access": "", "host": "Y.Event.API", "type": "method", "name": "hasSubscribers"}, {"url": "Y.Event.API.html#method__initEvents", "access": "protected", "host": "Y.Event.API", "type": "method", "name": "_initEvents"}, {"url": "Y.Event.API.html#method_on", "access": "", "host": "Y.Event.API", "type": "method", "name": "on"}, {"url": "Y.Event.API.html#method_publish", "access": "", "host": "Y.Event.API", "type": "method", "name": "publish"}, {"url": "Y.Event.API.html#method__resolveBubblePath", "access": "protected", "host": "Y.Event.API", "type": "method", "name": "_resolveBubblePath"}, {"url": "Y.Event.API.html#method__subscribe", "access": "protected", "host": "Y.Event.API", "type": "method", "name": "_subscribe"}, {"url": "Y.Event.API.html#method_subscribe", "access": "", "host": "Y.Event.API", "type": "method", "name": "subscribe"}, {"url": "Y.Event.API.html#property_TYPE_PATTERN", "access": "protected", "host": "Y.Event.API", "type": "property", "name": "TYPE_PATTERN"}]